datasette_events_forward/__init__.py
datasette_events_forward-0.1a4.dist-info/licenses/LICENSE
datasette_events_forward-0.1a4.dist-info/METADATA
datasette_events_forward-0.1a4.dist-info/WHEEL
datasette_events_forward-0.1a4.dist-info/entry_points.txt
datasette_events_forward-0.1a4.dist-info/top_level.txt
datasette_events_forward-0.1a4.dist-info/RECORD
