Metadata-Version: 2.4
Name: datasette-events-forward
Version: 0.1a4
Summary: Forward Datasette events to another instance
Author: Simon Willison
License-Expression: Apache-2.0
Project-URL: Homepage, https://github.com/datasette/datasette-events-forward
Project-URL: Changelog, https://github.com/datasette/datasette-events-forward/releases
Project-URL: Issues, https://github.com/datasette/datasette-events-forward/issues
Project-URL: CI, https://github.com/datasette/datasette-events-forward/actions
Classifier: Framework :: Datasette
Requires-Python: >=3.10
License-File: LICENSE
Requires-Dist: datasette>=1.0a20
Requires-Dist: python-ulid
Requires-Dist: aiolimiter
Requires-Dist: typing_extensions
Provides-Extra: test
Requires-Dist: pytest; extra == "test"
Requires-Dist: pytest-asyncio; extra == "test"
Requires-Dist: pytest-httpx; extra == "test"
Requires-Dist: datasette-test; extra == "test"
Dynamic: license-file
